djangomako/__init__.py
djangomako/backends.py
djangomako/tests.py
djangomako-1.3.1.dist-info/LICENSE
djangomako-1.3.1.dist-info/METADATA
djangomako-1.3.1.dist-info/WHEEL
djangomako-1.3.1.dist-info/top_level.txt
djangomako-1.3.1.dist-info/RECORD
