Metadata-Version: 2.1
Name: djangomako
Version: 1.3.1
Summary: The simple, elegant Django Mako library
Home-page: https://github.com/iamjazzar/django-mako
Author: Ahmed Jazzar
Author-email: me@ahmedjazzar.com
License: MIT License
Classifier: Development Status :: 5 - Production/Stable
Classifier: Intended Audience :: Developers
Classifier: Operating System :: OS Independent
Classifier: Programming Language :: Python :: 3
Classifier: Programming Language :: Python :: 3.7
Classifier: Programming Language :: Python :: 3.8
Classifier: Programming Language :: Python :: 3.9
Classifier: Programming Language :: Python :: 3.10
Classifier: Framework :: Django
Classifier: Framework :: Django :: 3.2
Classifier: Framework :: Django :: 4.0
Classifier: License :: OSI Approved :: MIT License
Classifier: Topic :: Software Development
License-File: LICENSE
Requires-Dist: Mako (==1.2.2)
